Metadata-Version: 2.1
Name: gwu-nn
Version: 0.2.0
Summary: Neural Network library for the George Washington University
Home-page: https://gwu-nn.readthedocs.io/en/latest/index.html
Author: Joel Klein
Author-email: jdk51405@gmail.com
License: MIT
Platform: UNKNOWN
Classifier: Programming Language :: Python :: 3.8
Classifier: License :: OSI Approved :: MIT License
Classifier: Operating System :: OS Independent
Requires-Python: >=3.7
